<Properties StartupConfiguration="{D1A69E23-BDDC-435D-B60B-3DF8989B7480}|Default">
  <MonoDevelop.Ide.Workspace ActiveConfiguration="Debug" />
  <MonoDevelop.Ide.ItemProperties.proyecto-Jardineria PreferredExecutionTarget="MonoDevelop.Default" />
  <MonoDevelop.Ide.DebuggingService.PinnedWatches />
  <MultiItemStartupConfigurations />
  <MonoDevelop.Ide.DebuggingService.Breakpoints>
    <BreakpointStore />
  </MonoDevelop.Ide.DebuggingService.Breakpoints>
  <MonoDevelop.Ide.Workbench ActiveDocument="BaseDeDatos.cs">
    <Files>
      <File FileName="Program.cs" Line="239" Column="30" />
      <File FileName="BaseDeDatos.cs" Line="13" Column="9" />
      <File FileName="Cliente.cs" />
      <File FileName="DetallePedido.cs" />
      <File FileName="Incidencia.cs" />
      <File FileName="Pedido.cs" />
      <File FileName="Producto.cs" />
    </Files>
    <Pads>
      <Pad Id="ProjectPad">
        <State name="__root__">
          <Node name="proyecto-Jardineria" expanded="True">
            <Node name="proyecto-Jardineria" expanded="True">
              <Node name="BaseDeDatos.cs" selected="True" />
            </Node>
          </Node>
        </State>
      </Pad>
    </Pads>
  </MonoDevelop.Ide.Workbench>
</Properties>